story_teller/__init__.py
story_teller/comedy.py
story_teller/horror.py
story_teller-1.0.1.dist-info/METADATA
story_teller-1.0.1.dist-info/WHEEL
story_teller-1.0.1.dist-info/top_level.txt
story_teller-1.0.1.dist-info/RECORD
