Metadata-Version: 2.1
Name: story-teller
Version: 1.0.1
Summary: Package that tells you stories
Home-page: UNKNOWN
Author: UNKNOWN
Author-email: UNKNOWN
License: UNKNOWN
Platform: UNKNOWN
